cricsummary/Viz.py
cricsummary/__init__.py
cricsummary/converters.py
cricsummary/duranz.py
cricsummary-2.0.2.dist-info/METADATA
cricsummary-2.0.2.dist-info/WHEEL
cricsummary-2.0.2.dist-info/top_level.txt
cricsummary-2.0.2.dist-info/RECORD
