Metadata-Version: 2.1
Name: cricsummary
Version: 2.0.2
Summary: Perform Analysis, Create summary table and charts from cricsheet data
Home-page: https://github.com/KunalDuran/cricsummary
Author: Kunal Duran
Author-email: kunalduran13@gmail.com
License: MIT
Platform: UNKNOWN
Classifier: License :: OSI Approved :: MIT License
Classifier: Programming Language :: Python :: 3
Classifier: Programming Language :: Python :: 3.7
Requires-Python: >=3.5
Requires-Dist: numpy
Requires-Dist: pandas
Requires-Dist: matplotlib
Requires-Dist: seaborn
